offlinebooks/__init__.py
offlinebooks/main.py
offlinebooks-0.0.8.dist-info/AGPL-3.0-or-later.txt
offlinebooks-0.0.8.dist-info/CC-BY-4.0.txt
offlinebooks-0.0.8.dist-info/CC-BY-SA-4.0.txt
offlinebooks-0.0.8.dist-info/METADATA
offlinebooks-0.0.8.dist-info/WHEEL
offlinebooks-0.0.8.dist-info/entry_points.txt
offlinebooks-0.0.8.dist-info/top_level.txt
offlinebooks-0.0.8.dist-info/RECORD
