Metadata-Version: 2.1
Name: offlinebooks
Version: 0.0.8
Summary: Keep your accounts offline
Home-page: https://github.com/Ian2020/offlinebooks
Author: Ian2020
License: AGPL-3.0-or-later AND CC-BY-4.0 AND CC-BY-SA-4.0
Project-URL: Source, https://github.com/Ian2020/offlinebooks
Project-URL: Changelog, https://github.com/Ian2020/offlinebooks/tags
Project-URL: Bug Tracker, https://github.com/Ian2020/offlinebooks/issues
Classifier: Development Status :: 4 - Beta
Classifier: Environment :: Console
Classifier: Intended Audience :: Developers
Classifier: License :: OSI Approved :: GNU Affero General Public License v3 or later (AGPLv3+)
Classifier: Operating System :: POSIX
Classifier: Programming Language :: Python :: 3
Classifier: Topic :: Office/Business :: Financial :: Accounting
Classifier: Topic :: Utilities
License-File: LICENSES/AGPL-3.0-or-later.txt
License-File: LICENSES/CC-BY-4.0.txt
License-File: LICENSES/CC-BY-SA-4.0.txt
Requires-Dist: pyxero (>=0.9.3)
Requires-Dist: pathvalidate (>=2.5.0)
Requires-Dist: tenacity (>=8.0.1)
